mmtrack/__init__.py
mmtrack/version.py
mmtrack/.mim/model-index.yml
mmtrack/.mim/configs/_base_/default_runtime.py
mmtrack/.mim/configs/_base_/datasets/coco_detection.py
mmtrack/.mim/configs/_base_/datasets/coco_instance.py
mmtrack/.mim/configs/_base_/datasets/coco_instance_semantic.py
mmtrack/.mim/configs/_base_/datasets/dancetrack.py
mmtrack/.mim/configs/_base_/datasets/imagenet_vid_dff_style.py
mmtrack/.mim/configs/_base_/datasets/imagenet_vid_fgfa_style.py
mmtrack/.mim/configs/_base_/datasets/lvis_v0.5_instance.py
mmtrack/.mim/configs/_base_/datasets/lvis_v1_instance.py
mmtrack/.mim/configs/_base_/datasets/mot_challenge.py
mmtrack/.mim/configs/_base_/datasets/mot_challenge_det.py
mmtrack/.mim/configs/_base_/datasets/mot_challenge_reid.py
mmtrack/.mim/configs/_base_/datasets/tao.py
mmtrack/.mim/configs/_base_/datasets/youtube_vis.py
mmtrack/.mim/configs/_base_/models/cascade_mask_rcnn_r50_fpn.py
mmtrack/.mim/configs/_base_/models/cascade_rcnn_r50_fpn.py
mmtrack/.mim/configs/_base_/models/faster_rcnn_r50_caffe_c4.py
mmtrack/.mim/configs/_base_/models/faster_rcnn_r50_dc5.py
mmtrack/.mim/configs/_base_/models/faster_rcnn_r50_fpn.py
mmtrack/.mim/configs/_base_/models/mask_rcnn_r50_fpn.py
mmtrack/.mim/configs/_base_/models/retinanet_r50_fpn.py
mmtrack/.mim/configs/_base_/models/yolox_x_8x8.py
mmtrack/.mim/configs/det/faster-rcnn_r101_fpn_4e_mot17-half.py
mmtrack/.mim/configs/det/faster-rcnn_r50_fpn_4e_mot15-half.py
mmtrack/.mim/configs/det/faster-rcnn_r50_fpn_4e_mot16-half.py
mmtrack/.mim/configs/det/faster-rcnn_r50_fpn_4e_mot17-half.py
mmtrack/.mim/configs/det/faster-rcnn_r50_fpn_4e_mot17.py
mmtrack/.mim/configs/det/faster-rcnn_r50_fpn_8e_mot20-half.py
mmtrack/.mim/configs/det/faster-rcnn_r50_fpn_8e_mot20.py
mmtrack/.mim/configs/mot/bytetrack/bytetrack_yolox_x_crowdhuman_mot17-private-half.py
mmtrack/.mim/configs/mot/bytetrack/bytetrack_yolox_x_crowdhuman_mot17-private.py
mmtrack/.mim/configs/mot/bytetrack/bytetrack_yolox_x_crowdhuman_mot20-private.py
mmtrack-0.14.0.dist-info/LICENSE
mmtrack-0.14.0.dist-info/METADATA
mmtrack-0.14.0.dist-info/WHEEL
mmtrack-0.14.0.dist-info/top_level.txt
mmtrack-0.14.0.dist-info/RECORD
