Metadata-Version: 2.1
Name: mmtrack
Version: 0.14.0
Summary: OpenMMLab Unified Video Perception Platform
Home-page: https://github.com/open-mmlab/mmtracking
Author: MMTracking Contributors
Author-email: openmmlab@gmail.com
License: Apache License 2.0
Keywords: computer vision,object tracking,video object detection
Platform: UNKNOWN
Classifier: Development Status :: 4 - Beta
Classifier: License :: OSI Approved :: Apache Software License
Classifier: Operating System :: OS Independent
Classifier: Programming Language :: Python :: 3
Classifier: Programming Language :: Python :: 3.6
Classifier: Programming Language :: Python :: 3.7
Classifier: Programming Language :: Python :: 3.8
Classifier: Programming Language :: Python :: 3.9
Requires-Dist: attributee
Requires-Dist: dotty-dict
Requires-Dist: lap
Requires-Dist: matplotlib
Requires-Dist: mmcls (<1.0.0,>=0.16.0)
Requires-Dist: motmetrics
Requires-Dist: packaging
Requires-Dist: pandas (<=1.3.5)
Requires-Dist: pycocotools
Requires-Dist: scipy (<=1.7.3)
Requires-Dist: seaborn
Requires-Dist: terminaltables
Requires-Dist: tqdm
Provides-Extra: all
Requires-Dist: cython ; extra == 'all'
Requires-Dist: numpy ; extra == 'all'
Requires-Dist: attributee ; extra == 'all'
Requires-Dist: dotty-dict ; extra == 'all'
Requires-Dist: lap ; extra == 'all'
Requires-Dist: matplotlib ; extra == 'all'
Requires-Dist: mmcls (<1.0.0,>=0.16.0) ; extra == 'all'
Requires-Dist: motmetrics ; extra == 'all'
Requires-Dist: packaging ; extra == 'all'
Requires-Dist: pandas (<=1.3.5) ; extra == 'all'
Requires-Dist: pycocotools ; extra == 'all'
Requires-Dist: scipy (<=1.7.3) ; extra == 'all'
Requires-Dist: seaborn ; extra == 'all'
Requires-Dist: terminaltables ; extra == 'all'
Requires-Dist: tqdm ; extra == 'all'
Requires-Dist: asynctest ; extra == 'all'
Requires-Dist: codecov ; extra == 'all'
Requires-Dist: flake8 ; extra == 'all'
Requires-Dist: interrogate ; extra == 'all'
Requires-Dist: isort (==4.3.21) ; extra == 'all'
Requires-Dist: kwarray ; extra == 'all'
Requires-Dist: pytest ; extra == 'all'
Requires-Dist: ubelt ; extra == 'all'
Requires-Dist: xdoctest (>=0.10.0) ; extra == 'all'
Requires-Dist: yapf ; extra == 'all'
Provides-Extra: build
Requires-Dist: cython ; extra == 'build'
Requires-Dist: numpy ; extra == 'build'
Provides-Extra: mim
Requires-Dist: mmcls (<1.0.0,>=0.16.0) ; extra == 'mim'
Requires-Dist: mmcv-full (<1.7.0,>=1.3.17) ; extra == 'mim'
Requires-Dist: mmdet (<3.0.0,>=2.19.1) ; extra == 'mim'
Provides-Extra: tests
Requires-Dist: asynctest ; extra == 'tests'
Requires-Dist: codecov ; extra == 'tests'
Requires-Dist: flake8 ; extra == 'tests'
Requires-Dist: interrogate ; extra == 'tests'
Requires-Dist: isort (==4.3.21) ; extra == 'tests'
Requires-Dist: kwarray ; extra == 'tests'
Requires-Dist: pytest ; extra == 'tests'
Requires-Dist: ubelt ; extra == 'tests'
Requires-Dist: xdoctest (>=0.10.0) ; extra == 'tests'
Requires-Dist: yapf ; extra == 'tests'
